ngsimple/__init__.py
ngsimple/wrapper.py
ngsimple-0.2.0.dist-info/LICENSE
ngsimple-0.2.0.dist-info/METADATA
ngsimple-0.2.0.dist-info/WHEEL
ngsimple-0.2.0.dist-info/top_level.txt
ngsimple-0.2.0.dist-info/RECORD
