Metadata-Version: 2.1
Name: ngsimple
Version: 0.2.0
Summary: The easiest way to call Netgen from Python
Home-page: https://github.com/kinnala/ngsimple
Author: Tom Gustafsson
License: LGPL-2.1-only
Project-URL: Code, https://github.com/kinnala/ngsimple
Project-URL: Issues, https://github.com/kinnala/ngsimple/issues
Classifier: Intended Audience :: Science/Research
Classifier: Operating System :: OS Independent
Classifier: Programming Language :: Python
Classifier: Programming Language :: Python :: 3
Classifier: Programming Language :: Python :: 3.6
Classifier: Programming Language :: Python :: 3.7
Classifier: Programming Language :: Python :: 3.8
Classifier: Topic :: Scientific/Engineering
Classifier: Topic :: Utilities
Requires-Python: >=3.6
License-File: LICENSE
Requires-Dist: docker
Requires-Dist: meshio >=4.0.4
Requires-Dist: importlib-metadata ; python_version < "3.8"
